BinaryTrees/Node.py
BinaryTrees/__init__.py
BinaryTreess-0.0.1.dist-info/LICENSE
BinaryTreess-0.0.1.dist-info/METADATA
BinaryTreess-0.0.1.dist-info/WHEEL
BinaryTreess-0.0.1.dist-info/top_level.txt
BinaryTreess-0.0.1.dist-info/RECORD
